pandasnet_netstandard/__init__.py
pandasnet_netstandard/libs/PandasNet.deps.json
pandasnet_netstandard/libs/PandasNet.dll
pandasnet_netstandard/libs/PandasNet.pdb
tests/libs/LibForTests.deps.json
tests/libs/LibForTests.dll
tests/libs/LibForTests.pdb
pandasnet_netstandard-0.7.2.dist-info/LICENSE
pandasnet_netstandard-0.7.2.dist-info/METADATA
pandasnet_netstandard-0.7.2.dist-info/WHEEL
pandasnet_netstandard-0.7.2.dist-info/top_level.txt
pandasnet_netstandard-0.7.2.dist-info/RECORD
