Metadata-Version: 2.1
Name: pandasnet-netstandard
Version: 0.7.2
Summary: Extensions of pythonnet package to support pandas DataFrame conversions
Home-page: https://github.com/Filimindji/pandasnet_netstandard
Author: Damien HOFFSCHIR
Author-email: damien.hoffschir@outlook.com
Classifier: License :: OSI Approved :: MIT License
Classifier: Programming Language :: C#
Classifier: Programming Language :: Python :: 3
Classifier: Programming Language :: Python :: 3.6
Classifier: Programming Language :: Python :: 3.7
Classifier: Programming Language :: Python :: 3.8
Classifier: Programming Language :: Python :: 3.9
Classifier: Operating System :: Microsoft :: Windows
Classifier: Operating System :: POSIX :: Linux
Classifier: Operating System :: MacOS :: MacOS X
License-File: LICENSE
Requires-Dist: pycparser
Requires-Dist: pythonnet
Requires-Dist: pandas
